{
  "app.title": "Domain counter",
  "app.form.pin": "Pin для доступа к сервису",
  "app.form.unlock": "Активировать",
  "app.form.select_search_engine": "Выберите поисковые движки",
  "app.form.yandex": "Yandex",
  "app.form.google": "Google",
  "app.form.type_words": "Ввод слов вручную",
  "app.form.words_for_processing": "Введите ключевые слова",
  "app.form.use_file": "Использовать файл",
  "app.form.input_file": "Файл с ключевыми словами",
  "app.form.loading_caption": "Пожалуйста, подождите некоторое время пока файл будет загружен...",
  "app.form.start_processing": "Запустить обработку"
}